config_poetry/__init__.py
config_poetry/__main__.py
config_poetry/DP_CPU_reports.py
config_poetry/EOL_errors.py
config_poetry/generate_output.py
config_poetry/MP_CPU_reports.py
config_poetry/NPC_errors.py
config_poetry/PanoramaTSF.py
config_poetry/parser_1.py
config_poetry/platformView.py
config_poetry/SMC_errors.py
config_poetry/TSFParser.sh
config_poetry-0.2.0.dist-info/entry_points.txt
config_poetry-0.2.0.dist-info/METADATA
config_poetry-0.2.0.dist-info/WHEEL
config_poetry-0.2.0.dist-info/RECORD
