Metadata-Version: 2.1
Name: config-poetry
Version: 0.2.0
Summary: 
Author: Omar Fareed
Author-email: ofareed@paloaltonetworks.com
Requires-Python: >=3.12,<4.0
Classifier: Programming Language :: Python :: 3
Classifier: Programming Language :: Python :: 3.12
Requires-Dist: requests (>=2.32.3,<3.0.0)
